pydantic_aioredis/__init__.py
pydantic_aioredis/abstract.py
pydantic_aioredis/config.py
pydantic_aioredis/ext/FastAPI/__init__.py
pydantic_aioredis/ext/FastAPI/crudrouter.py
pydantic_aioredis/ext/FastAPI/model.py
pydantic_aioredis/ext/__init__.py
pydantic_aioredis/model.py
pydantic_aioredis/store.py
pydantic_aioredis/types.py
pydantic_aioredis/utils.py
pydantic_aioredis-1.4.0.dist-info/LICENSE
pydantic_aioredis-1.4.0.dist-info/METADATA
pydantic_aioredis-1.4.0.dist-info/WHEEL
pydantic_aioredis-1.4.0.dist-info/RECORD
