Metadata-Version: 2.1
Name: pydantic-aioredis
Version: 1.4.0
Summary: Use your pydantic models as an ORM, storing data in Redis.
Home-page: https://github.com/andrewthetechie/pydantic-aioredis
License: MIT
Author: Andrew Herrington
Author-email: andrew.the.techie@gmail.com
Requires-Python: >=3.8,<4.0
Classifier: Development Status :: 4 - Beta
Classifier: Framework :: AsyncIO
Classifier: Intended Audience :: Developers
Classifier: License :: OSI Approved :: MIT License
Classifier: Programming Language :: Python
Classifier: Programming Language :: Python :: 3
Classifier: Programming Language :: Python :: 3.8
Classifier: Programming Language :: Python :: 3.9
Classifier: Programming Language :: Python :: 3.10
Classifier: Programming Language :: Python :: 3.11
Classifier: Programming Language :: Python :: 3.12
Classifier: Programming Language :: Python :: 3.7
Provides-Extra: fastapi
Provides-Extra: fastapi-crudrouter
Requires-Dist: anyio (>=3.6.2,<5.0.0)
Requires-Dist: fastapi (>=0.110) ; extra == "fastapi"
Requires-Dist: fastapi-crudrouter (>=0.8.6,<0.9.0) ; extra == "fastapi-crudrouter"
Requires-Dist: pydantic (>=1.10.2,<2.0.0)
Requires-Dist: redis (>=4.4.4,<6.0.0)
Project-URL: Changelog, https://github.com/andrewthetechie/pydantic-aioredis/releases
Project-URL: Documentation, https://pydantic-aioredis.readthedocs.io/en/latest/
Project-URL: Repository, https://github.com/andrewthetechie/pydantic-aioredis
